chemkinlib/__init__.py
chemkinlib/_version.py
chemkinlib/config.py
chemkinlib/data/A_arr.xml
chemkinlib/data/A_mod_arr.xml
chemkinlib/data/E_arr.xml
chemkinlib/data/E_mod_arr.xml
chemkinlib/data/NASA_poly_coeff.sqlite
chemkinlib/data/NASA_poly_coeffs.sqlite
chemkinlib/data/b_mod_arr.xml
chemkinlib/data/k_const.xml
chemkinlib/data/rev_rxn.xml
chemkinlib/data/rxn.xml
chemkinlib/data/rxns.xml
chemkinlib/data/rxns_mixed.xml
chemkinlib/data/rxns_reversible.xml
chemkinlib/data/rxnset_long.xml
chemkinlib/data/rxnsys.xml
chemkinlib/data/unrecognized_rxn.xml
chemkinlib/reactions/ReactionRateCoeffs.py
chemkinlib/reactions/ReactionSystems.py
chemkinlib/reactions/Reactions.py
chemkinlib/reactions/__init__.py
chemkinlib/reactions/test_ReactionRateCoeffs.py
chemkinlib/reactions/test_ReactionSystem.py
chemkinlib/reactions/test_ReactionSystems.py
chemkinlib/reactions/test_Reactions.py
chemkinlib/utils/Parser.py
chemkinlib/utils/__init__.py
chemkinlib/utils/test_Parser.py
chemkinlib/utils/test_visualizer.py
chemkinlib/utils/visualizer.py
chemkinlib11-0.1.3.dist-info/DESCRIPTION.rst
chemkinlib11-0.1.3.dist-info/METADATA
chemkinlib11-0.1.3.dist-info/RECORD
chemkinlib11-0.1.3.dist-info/WHEEL
chemkinlib11-0.1.3.dist-info/metadata.json
chemkinlib11-0.1.3.dist-info/top_level.txt
