Metadata-Version: 2.0
Name: chemkinlib11
Version: 0.1.3
Summary: Chemical kinetics code
Home-page: https://github.com/cs207-group11/cs207-FinalProject
Author: ChemKinLib Developers
Author-email: hsim13372@gmail.com
License: MIT
Platform: UNKNOWN
Requires-Dist: graphviz
Requires-Dist: imageio
Requires-Dist: jupyter
Requires-Dist: moviepy
Requires-Dist: numpy
Requires-Dist: pytest
Requires-Dist: scipy
